httpx_moex/__init__.py
httpx_moex/candles.py
httpx_moex/client.py
httpx_moex/history.py
httpx_moex/reference.py
httpx_moex/request_helpers.py
httpx_moex-0.1.0.dist-info/METADATA
httpx_moex-0.1.0.dist-info/WHEEL
httpx_moex-0.1.0.dist-info/licenses/LICENSE
httpx_moex-0.1.0.dist-info/RECORD
